postcode_eu_ai_tools/__init__.py
postcode_eu_ai_tools/__main__.py
postcode_eu_ai_tools/py.typed
postcode_eu_ai_tools/tools.py
postcode_eu_ai_tools/utils.py
postcode_eu_ai_tools-1.0.0.dist-info/WHEEL
postcode_eu_ai_tools-1.0.0.dist-info/entry_points.txt
postcode_eu_ai_tools-1.0.0.dist-info/METADATA
postcode_eu_ai_tools-1.0.0.dist-info/RECORD
