Metadata-Version: 2.4
Name: postcode-eu-ai-tools
Version: 1.0.0
Summary: AI tools / MCP server for address validation via the Postcode.eu API
Author: Postcode.eu
Author-email: Postcode.eu <tech@postcode.eu>
License-Expression: BSD-2-Clause
Requires-Dist: mcp>=1.16.0
Requires-Dist: platformdirs>=4.5.0
Requires-Dist: postcode-eu-api-client>=1.0.2
Requires-Python: >=3.11
Project-URL: Homepage, https://www.postcode.eu/products/address-api
Project-URL: Issues, https://github.com/postcode-nl/postcode-eu-ai-tools-python/issues
Project-URL: Repository, https://github.com/postcode-nl/postcode-eu-ai-tools-python
